{
  "id": 2814688,
  "name": "nbval",
  "ecosystem": "pypi",
  "description": "A py.test plugin to validate Jupyter notebooks",
  "homepage": "https://github.com/computationalmodelling/nbval",
  "licenses": "BSD License",
  "normalized_licenses": [
    "BSD-3-Clause"
  ],
  "repository_url": "https://github.com/computationalmodelling/nbval",
  "keywords_array": [],
  "namespace": null,
  "versions_count": 19,
  "first_release_published_at": "2016-03-18T17:24:32.000Z",
  "latest_release_published_at": "2024-03-04T14:36:57.000Z",
  "latest_release_number": "0.11.0",
  "last_synced_at": "2024-10-21T15:00:24.421Z",
  "created_at": "2022-04-10T11:43:07.024Z",
  "updated_at": "2024-10-21T15:00:24.421Z",
  "registry_url": "https://pypi.org/project/nbval/",
  "install_command": "pip install nbval --index-url https://pypi.org/simple",
  "documentation_url": "https://nbval.readthedocs.io/",
  "metadata": {
    "funding": null,
    "documentation": null,
    "classifiers": [
      "Framework :: IPython",
      "Framework :: Pytest",
      "License :: OSI Approved :: BSD License",
      "Programming Language :: Python :: 3",
      "Topic :: Software Development :: Testing"
    ],
    "normalized_name": "nbval"
  },
  "repo_metadata": {
    "id": 30111162,
    "uuid": "33660979",
    "full_name": "computationalmodelling/nbval",
    "owner": "computationalmodelling",
    "description": "A py.test plugin to validate Jupyter notebooks",
    "archived": false,
    "fork": false,
    "pushed_at": "2024-03-04T14:36:27.000Z",
    "size": 930,
    "stargazers_count": 433,
    "open_issues_count": 49,
    "forks_count": 51,
    "subscribers_count": 11,
    "default_branch": "master",
    "last_synced_at": "2024-05-17T15:06:22.999Z",
    "etag": null,
    "topics": [
      "ipython-notebook",
      "jupyter-notebook",
      "pytest",
      "pytest-plugin",
      "python",
      "testing"
    ],
    "latest_commit_sha": null,
    "homepage": "",
    "language": "Python",
    "has_issues": true,
    "has_wiki": null,
    "has_pages": null,
    "mirror_url": null,
    "source_name": null,
    "license": "other",
    "status": null,
    "scm": "git",
    "pull_requests_enabled": true,
    "icon_url": "https://github.com/computationalmodelling.png",
    "metadata": {
      "files": {
        "readme": "README.md",
        "changelog": null,
        "contributing": null,
        "funding": null,
        "license": "LICENSE",
        "code_of_conduct": null,
        "threat_model": null,
        "audit": null,
        "citation": null,
        "codeowners": null,
        "security": null,
        "support": null,
        "governance": null,
        "roadmap": null,
        "authors": null,
        "dei": null,
        "publiccode": null,
        "codemeta": null
      }
    },
    "created_at": "2015-04-09T09:40:33.000Z",
    "updated_at": "2024-06-18T12:57:57.216Z",
    "dependencies_parsed_at": "2024-01-03T07:09:13.018Z",
    "dependency_job_id": "d9f2af9b-7af3-407c-b816-a0dda17a2ff9",
    "html_url": "https://github.com/computationalmodelling/nbval",
    "commit_stats": {
      "total_commits": 382,
      "total_committers": 37,
      "mean_commits": "10.324324324324325",
      "dds": 0.7408376963350785,
      "last_synced_commit": "d7bc34893a9251fbfd4b270347197619c32fe6ea"
    },
    "previous_names": [],
    "tags_count": 18,
    "template": false,
    "template_full_name": null,
    "repository_url": "https://repos.ecosyste.ms/api/v1/hosts/GitHub/repositories/computationalmodelling%2Fnbval",
    "tags_url": "https://repos.ecosyste.ms/api/v1/hosts/GitHub/repositories/computationalmodelling%2Fnbval/tags",
    "releases_url": "https://repos.ecosyste.ms/api/v1/hosts/GitHub/repositories/computationalmodelling%2Fnbval/releases",
    "manifests_url": "https://repos.ecosyste.ms/api/v1/hosts/GitHub/repositories/computationalmodelling%2Fnbval/manifests",
    "owner_url": "https://repos.ecosyste.ms/api/v1/hosts/GitHub/owners/computationalmodelling",
    "download_url": "https://codeload.github.com/computationalmodelling/nbval/tar.gz/refs/heads/master",
    "host": {
      "name": "GitHub",
      "url": "https://github.com",
      "kind": "github",
      "repositories_count": 215684760,
      "owners_count": 15915920,
      "icon_url": "https://github.com/github.png",
      "version": null,
      "created_at": "2022-05-30T11:31:42.601Z",
      "updated_at": "2022-07-04T15:15:14.044Z",
      "host_url": "https://repos.ecosyste.ms/api/v1/hosts/GitHub",
      "repositories_url": "https://repos.ecosyste.ms/api/v1/hosts/GitHub/repositories",
      "repository_names_url": "https://repos.ecosyste.ms/api/v1/hosts/GitHub/repository_names",
      "owners_url": "https://repos.ecosyste.ms/api/v1/hosts/GitHub/owners"
    },
    "owner_record": {
      "login": "computationalmodelling",
      "name": "Computational Modelling Group (Hans Fangohr)",
      "uuid": "11869420",
      "kind": "organization",
      "description": "Max Planck Institute for the Structure and Dynamics of Matter / University of Southampton (UK) / European XFEL",
      "email": "fangohr@soton.ac.uk",
      "website": "http://cmg.soton.ac.uk",
      "location": "Southampton, UK",
      "twitter": "ProfCompMod",
      "company": null,
      "icon_url": "https://avatars.githubusercontent.com/u/11869420?v=4",
      "repositories_count": 6,
      "last_synced_at": "2023-03-01T06:20:16.134Z",
      "metadata": {
        "has_sponsors_listing": false
      },
      "html_url": "https://github.com/computationalmodelling",
      "funding_links": [],
      "total_stars": null,
      "followers": null,
      "following": null,
      "created_at": "2022-11-12T05:20:02.934Z",
      "updated_at": "2023-03-01T06:20:16.172Z",
      "owner_url": "https://repos.ecosyste.ms/api/v1/hosts/GitHub/owners/computationalmodelling",
      "repositories_url": "https://repos.ecosyste.ms/api/v1/hosts/GitHub/owners/computationalmodelling/repositories"
    },
    "tags": [
      {
        "name": "0.11.0",
        "sha": "373e9afbe129437b583b2257be9206baa4c0fbb7",
        "kind": "commit",
        "published_at": "2024-03-04T14:35:29.000Z",
        "download_url": "https://codeload.github.com/computationalmodelling/nbval/tar.gz/0.11.0",
        "html_url": "https://github.com/computationalmodelling/nbval/releases/tag/0.11.0",
        "dependencies_parsed_at": null,
        "dependency_job_id": null,
        "tag_url": "https://repos.ecosyste.ms/api/v1/hosts/GitHub/repositories/computationalmodelling%2Fnbval/tags/0.11.0",
        "manifests_url": "https://repos.ecosyste.ms/api/v1/hosts/GitHub/repositories/computationalmodelling%2Fnbval/tags/0.11.0/manifests"
      },
      {
        "name": "0.10.0",
        "sha": "d7bc34893a9251fbfd4b270347197619c32fe6ea",
        "kind": "tag",
        "published_at": "2023-01-11T11:27:30.000Z",
        "download_url": "https://codeload.github.com/computationalmodelling/nbval/tar.gz/0.10.0",
        "html_url": "https://github.com/computationalmodelling/nbval/releases/tag/0.10.0",
        "dependencies_parsed_at": null,
        "dependency_job_id": null,
        "tag_url": "https://repos.ecosyste.ms/api/v1/hosts/GitHub/repositories/computationalmodelling%2Fnbval/tags/0.10.0",
        "manifests_url": "https://repos.ecosyste.ms/api/v1/hosts/GitHub/repositories/computationalmodelling%2Fnbval/tags/0.10.0/manifests"
      },
      {
        "name": "0.9.6",
        "sha": "f88b4389632d82c363924dce2bbc2913b1be526c",
        "kind": "commit",
        "published_at": "2020-07-30T10:56:09.000Z",
        "download_url": "https://codeload.github.com/computationalmodelling/nbval/tar.gz/0.9.6",
        "html_url": "https://github.com/computationalmodelling/nbval/releases/tag/0.9.6",
        "dependencies_parsed_at": null,
        "dependency_job_id": null,
        "tag_url": "https://repos.ecosyste.ms/api/v1/hosts/GitHub/repositories/computationalmodelling%2Fnbval/tags/0.9.6",
        "manifests_url": "https://repos.ecosyste.ms/api/v1/hosts/GitHub/repositories/computationalmodelling%2Fnbval/tags/0.9.6/manifests"
      },
      {
        "name": "0.9.5",
        "sha": "8593e7d9de17d065036ac9a29aaa4a5caac6d5a2",
        "kind": "commit",
        "published_at": "2020-02-12T12:03:42.000Z",
        "download_url": "https://codeload.github.com/computationalmodelling/nbval/tar.gz/0.9.5",
        "html_url": "https://github.com/computationalmodelling/nbval/releases/tag/0.9.5",
        "dependencies_parsed_at": null,
        "dependency_job_id": null,
        "tag_url": "https://repos.ecosyste.ms/api/v1/hosts/GitHub/repositories/computationalmodelling%2Fnbval/tags/0.9.5",
        "manifests_url": "https://repos.ecosyste.ms/api/v1/hosts/GitHub/repositories/computationalmodelling%2Fnbval/tags/0.9.5/manifests"
      },
      {
        "name": "0.9.4",
        "sha": "a7a65bf7b5b6693269ba67dd5c68a5ef45f4a3d1",
        "kind": "commit",
        "published_at": "2019-12-16T14:52:24.000Z",
        "download_url": "https://codeload.github.com/computationalmodelling/nbval/tar.gz/0.9.4",
        "html_url": "https://github.com/computationalmodelling/nbval/releases/tag/0.9.4",
        "dependencies_parsed_at": null,
        "dependency_job_id": null,
        "tag_url": "https://repos.ecosyste.ms/api/v1/hosts/GitHub/repositories/computationalmodelling%2Fnbval/tags/0.9.4",
        "manifests_url": "https://repos.ecosyste.ms/api/v1/hosts/GitHub/repositories/computationalmodelling%2Fnbval/tags/0.9.4/manifests"
      },
      {
        "name": "0.9.3",
        "sha": "b733cc5153b9ad8554fd03252753104d16c48bcc",
        "kind": "commit",
        "published_at": "2019-09-27T08:32:50.000Z",
        "download_url": "https://codeload.github.com/computationalmodelling/nbval/tar.gz/0.9.3",
        "html_url": "https://github.com/computationalmodelling/nbval/releases/tag/0.9.3",
        "dependencies_parsed_at": null,
        "dependency_job_id": null,
        "tag_url": "https://repos.ecosyste.ms/api/v1/hosts/GitHub/repositories/computationalmodelling%2Fnbval/tags/0.9.3",
        "manifests_url": "https://repos.ecosyste.ms/api/v1/hosts/GitHub/repositories/computationalmodelling%2Fnbval/tags/0.9.3/manifests"
      },
      {
        "name": "0.9.2",
        "sha": "f2960e0c53fcbefd972a7c5415c9143bb447a52d",
        "kind": "commit",
        "published_at": "2019-07-03T12:43:35.000Z",
        "download_url": "https://codeload.github.com/computationalmodelling/nbval/tar.gz/0.9.2",
        "html_url": "https://github.com/computationalmodelling/nbval/releases/tag/0.9.2",
        "dependencies_parsed_at": null,
        "dependency_job_id": null,
        "tag_url": "https://repos.ecosyste.ms/api/v1/hosts/GitHub/repositories/computationalmodelling%2Fnbval/tags/0.9.2",
        "manifests_url": "https://repos.ecosyste.ms/api/v1/hosts/GitHub/repositories/computationalmodelling%2Fnbval/tags/0.9.2/manifests"
      },
      {
        "name": "0.9.1",
        "sha": "11ffb5e55de3025ec6106d6aef13b546dd3df304",
        "kind": "commit",
        "published_at": "2018-06-04T15:04:37.000Z",
        "download_url": "https://codeload.github.com/computationalmodelling/nbval/tar.gz/0.9.1",
        "html_url": "https://github.com/computationalmodelling/nbval/releases/tag/0.9.1",
        "dependencies_parsed_at": null,
        "dependency_job_id": null,
        "tag_url": "https://repos.ecosyste.ms/api/v1/hosts/GitHub/repositories/computationalmodelling%2Fnbval/tags/0.9.1",
        "manifests_url": "https://repos.ecosyste.ms/api/v1/hosts/GitHub/repositories/computationalmodelling%2Fnbval/tags/0.9.1/manifests"
      },
      {
        "name": "0.9",
        "sha": "0ec52867a580da95048d483085f7aa1265513673",
        "kind": "commit",
        "published_at": "2018-01-16T10:20:05.000Z",
        "download_url": "https://codeload.github.com/computationalmodelling/nbval/tar.gz/0.9",
        "html_url": "https://github.com/computationalmodelling/nbval/releases/tag/0.9",
        "dependencies_parsed_at": null,
        "dependency_job_id": null,
        "tag_url": "https://repos.ecosyste.ms/api/v1/hosts/GitHub/repositories/computationalmodelling%2Fnbval/tags/0.9",
        "manifests_url": "https://repos.ecosyste.ms/api/v1/hosts/GitHub/repositories/computationalmodelling%2Fnbval/tags/0.9/manifests"
      },
      {
        "name": "0.8",
        "sha": "6f2d05381a131cb41ee30ca46ae237a4a732be8d",
        "kind": "commit",
        "published_at": "2018-01-15T14:19:56.000Z",
        "download_url": "https://codeload.github.com/computationalmodelling/nbval/tar.gz/0.8",
        "html_url": "https://github.com/computationalmodelling/nbval/releases/tag/0.8",
        "dependencies_parsed_at": null,
        "dependency_job_id": null,
        "tag_url": "https://repos.ecosyste.ms/api/v1/hosts/GitHub/repositories/computationalmodelling%2Fnbval/tags/0.8",
        "manifests_url": "https://repos.ecosyste.ms/api/v1/hosts/GitHub/repositories/computationalmodelling%2Fnbval/tags/0.8/manifests"
      },
      {
        "name": "0.7",
        "sha": "e594ec933f1c12ef23ace505a651a1eefbb5de70",
        "kind": "commit",
        "published_at": "2017-08-30T11:56:47.000Z",
        "download_url": "https://codeload.github.com/computationalmodelling/nbval/tar.gz/0.7",
        "html_url": "https://github.com/computationalmodelling/nbval/releases/tag/0.7",
        "dependencies_parsed_at": null,
        "dependency_job_id": null,
        "tag_url": "https://repos.ecosyste.ms/api/v1/hosts/GitHub/repositories/computationalmodelling%2Fnbval/tags/0.7",
        "manifests_url": "https://repos.ecosyste.ms/api/v1/hosts/GitHub/repositories/computationalmodelling%2Fnbval/tags/0.7/manifests"
      },
      {
        "name": "0.6",
        "sha": "89d1d805da40b9b1430703bea6669425c68d5831",
        "kind": "commit",
        "published_at": "2017-05-15T14:03:39.000Z",
        "download_url": "https://codeload.github.com/computationalmodelling/nbval/tar.gz/0.6",
        "html_url": "https://github.com/computationalmodelling/nbval/releases/tag/0.6",
        "dependencies_parsed_at": null,
        "dependency_job_id": null,
        "tag_url": "https://repos.ecosyste.ms/api/v1/hosts/GitHub/repositories/computationalmodelling%2Fnbval/tags/0.6",
        "manifests_url": "https://repos.ecosyste.ms/api/v1/hosts/GitHub/repositories/computationalmodelling%2Fnbval/tags/0.6/manifests"
      },
      {
        "name": "0.5",
        "sha": "1997b75d5298e6a30f0f42f0fa3cbcb6fe734801",
        "kind": "commit",
        "published_at": "2017-02-24T14:13:46.000Z",
        "download_url": "https://codeload.github.com/computationalmodelling/nbval/tar.gz/0.5",
        "html_url": "https://github.com/computationalmodelling/nbval/releases/tag/0.5",
        "dependencies_parsed_at": null,
        "dependency_job_id": null,
        "tag_url": "https://repos.ecosyste.ms/api/v1/hosts/GitHub/repositories/computationalmodelling%2Fnbval/tags/0.5",
        "manifests_url": "https://repos.ecosyste.ms/api/v1/hosts/GitHub/repositories/computationalmodelling%2Fnbval/tags/0.5/manifests"
      },
      {
        "name": "v0.4.0",
        "sha": "f5f311e4fa98135c89f527728a1affb03383f1c9",
        "kind": "commit",
        "published_at": "2017-01-17T10:23:47.000Z",
        "download_url": "https://codeload.github.com/computationalmodelling/nbval/tar.gz/v0.4.0",
        "html_url": "https://github.com/computationalmodelling/nbval/releases/tag/v0.4.0",
        "dependencies_parsed_at": null,
        "dependency_job_id": null,
        "tag_url": "https://repos.ecosyste.ms/api/v1/hosts/GitHub/repositories/computationalmodelling%2Fnbval/tags/v0.4.0",
        "manifests_url": "https://repos.ecosyste.ms/api/v1/hosts/GitHub/repositories/computationalmodelling%2Fnbval/tags/v0.4.0/manifests"
      },
      {
        "name": "v0.3.6",
        "sha": "6574931783cf869b967faacbc253bfc152f05ae1",
        "kind": "tag",
        "published_at": "2016-10-18T11:58:19.000Z",
        "download_url": "https://codeload.github.com/computationalmodelling/nbval/tar.gz/v0.3.6",
        "html_url": "https://github.com/computationalmodelling/nbval/releases/tag/v0.3.6",
        "dependencies_parsed_at": null,
        "dependency_job_id": null,
        "tag_url": "https://repos.ecosyste.ms/api/v1/hosts/GitHub/repositories/computationalmodelling%2Fnbval/tags/v0.3.6",
        "manifests_url": "https://repos.ecosyste.ms/api/v1/hosts/GitHub/repositories/computationalmodelling%2Fnbval/tags/v0.3.6/manifests"
      },
      {
        "name": "v0.3.5",
        "sha": "e70cb4116f029c608133f06265b7966d6afa9b7b",
        "kind": "tag",
        "published_at": "2016-10-17T14:31:44.000Z",
        "download_url": "https://codeload.github.com/computationalmodelling/nbval/tar.gz/v0.3.5",
        "html_url": "https://github.com/computationalmodelling/nbval/releases/tag/v0.3.5",
        "dependencies_parsed_at": null,
        "dependency_job_id": null,
        "tag_url": "https://repos.ecosyste.ms/api/v1/hosts/GitHub/repositories/computationalmodelling%2Fnbval/tags/v0.3.5",
        "manifests_url": "https://repos.ecosyste.ms/api/v1/hosts/GitHub/repositories/computationalmodelling%2Fnbval/tags/v0.3.5/manifests"
      },
      {
        "name": "v0.3.4",
        "sha": "f157464e7db7384310a4f3f4cb29bf33083c2f88",
        "kind": "tag",
        "published_at": "2016-10-17T14:23:27.000Z",
        "download_url": "https://codeload.github.com/computationalmodelling/nbval/tar.gz/v0.3.4",
        "html_url": "https://github.com/computationalmodelling/nbval/releases/tag/v0.3.4",
        "dependencies_parsed_at": null,
        "dependency_job_id": null,
        "tag_url": "https://repos.ecosyste.ms/api/v1/hosts/GitHub/repositories/computationalmodelling%2Fnbval/tags/v0.3.4",
        "manifests_url": "https://repos.ecosyste.ms/api/v1/hosts/GitHub/repositories/computationalmodelling%2Fnbval/tags/v0.3.4/manifests"
      },
      {
        "name": "v0.3",
        "sha": "7fe58b1f8edfeec096377b21064e4d488a443cdb",
        "kind": "tag",
        "published_at": "2016-03-18T14:43:39.000Z",
        "download_url": "https://codeload.github.com/computationalmodelling/nbval/tar.gz/v0.3",
        "html_url": "https://github.com/computationalmodelling/nbval/releases/tag/v0.3",
        "dependencies_parsed_at": null,
        "dependency_job_id": null,
        "tag_url": "https://repos.ecosyste.ms/api/v1/hosts/GitHub/repositories/computationalmodelling%2Fnbval/tags/v0.3",
        "manifests_url": "https://repos.ecosyste.ms/api/v1/hosts/GitHub/repositories/computationalmodelling%2Fnbval/tags/v0.3/manifests"
      }
    ]
  },
  "repo_metadata_updated_at": "2024-09-07T19:30:08.040Z",
  "dependent_packages_count": 193,
  "downloads": 224548,
  "downloads_period": "last-month",
  "dependent_repos_count": 719,
  "rankings": {
    "downloads": 1.0848701060757662,
    "dependent_repos_count": 0.45908573967294414,
    "dependent_packages_count": 0.11562581284566707,
    "stargazers_count": 3.1794250606133674,
    "forks_count": 5.76567538244342,
    "docker_downloads_count": 1.3861807218164455,
    "average": 1.9984771372446017
  },
  "purl": "pkg:pypi/nbval",
  "advisories": [],
  "docker_usage_url": "https://docker.ecosyste.ms/usage/pypi/nbval",
  "docker_dependents_count": 18,
  "docker_downloads_count": 9379,
  "usage_url": "https://repos.ecosyste.ms/usage/pypi/nbval",
  "dependent_repositories_url": "https://repos.ecosyste.ms/api/v1/usage/pypi/nbval/dependencies",
  "status": null,
  "funding_links": [],
  "critical": null,
  "versions_url": "https://packages.ecosyste.ms/api/v1/registries/pypi.org/packages/nbval/versions",
  "version_numbers_url": "https://packages.ecosyste.ms/api/v1/registries/pypi.org/packages/nbval/version_numbers",
  "dependent_packages_url": "https://packages.ecosyste.ms/api/v1/registries/pypi.org/packages/nbval/dependent_packages",
  "related_packages_url": "https://packages.ecosyste.ms/api/v1/registries/pypi.org/packages/nbval/related_packages",
  "maintainers": [
    {
      "uuid": "minrk",
      "login": "minrk",
      "name": null,
      "email": null,
      "url": null,
      "packages_count": 89,
      "html_url": "https://pypi.org/user/minrk/",
      "role": null,
      "created_at": "2023-01-12T12:05:47.381Z",
      "updated_at": "2023-01-12T12:05:47.381Z",
      "packages_url": "https://packages.ecosyste.ms/api/v1/registries/pypi.org/maintainers/minrk/packages"
    },
    {
      "uuid": "takowl",
      "login": "takowl",
      "name": null,
      "email": null,
      "url": null,
      "packages_count": 112,
      "html_url": "https://pypi.org/user/takowl/",
      "role": null,
      "created_at": "2022-12-08T08:35:10.608Z",
      "updated_at": "2022-12-08T08:35:10.608Z",
      "packages_url": "https://packages.ecosyste.ms/api/v1/registries/pypi.org/maintainers/takowl/packages"
    },
    {
      "uuid": "vidartf",
      "login": "vidartf",
      "name": null,
      "email": null,
      "url": null,
      "packages_count": 26,
      "html_url": "https://pypi.org/user/vidartf/",
      "role": null,
      "created_at": "2022-12-08T08:35:10.612Z",
      "updated_at": "2022-12-08T08:35:10.612Z",
      "packages_url": "https://packages.ecosyste.ms/api/v1/registries/pypi.org/maintainers/vidartf/packages"
    },
    {
      "uuid": "fangohr",
      "login": "fangohr",
      "name": null,
      "email": null,
      "url": null,
      "packages_count": 18,
      "html_url": "https://pypi.org/user/fangohr/",
      "role": null,
      "created_at": "2022-12-08T08:35:10.598Z",
      "updated_at": "2022-12-08T08:35:10.598Z",
      "packages_url": "https://packages.ecosyste.ms/api/v1/registries/pypi.org/maintainers/fangohr/packages"
    },
    {
      "uuid": "marijanbeg",
      "login": "marijanbeg",
      "name": null,
      "email": null,
      "url": null,
      "packages_count": 12,
      "html_url": "https://pypi.org/user/marijanbeg/",
      "role": null,
      "created_at": "2022-12-08T08:35:10.601Z",
      "updated_at": "2022-12-08T08:35:10.601Z",
      "packages_url": "https://packages.ecosyste.ms/api/v1/registries/pypi.org/maintainers/marijanbeg/packages"
    }
  ]
}