{
  "id": 2866382,
  "name": "pybtex-docutils",
  "ecosystem": "pypi",
  "description": "A docutils backend for pybtex.",
  "homepage": "https://github.com/mcmtroffaes/pybtex-docutils",
  "licenses": "MIT",
  "normalized_licenses": [
    "MIT"
  ],
  "repository_url": "https://github.com/mcmtroffaes/pybtex-docutils",
  "keywords_array": [],
  "namespace": null,
  "versions_count": 8,
  "first_release_published_at": "2013-08-07T11:27:28.000Z",
  "latest_release_published_at": "2023-08-22T06:43:20.000Z",
  "latest_release_number": "1.0.3",
  "last_synced_at": "2024-10-12T06:34:18.667Z",
  "created_at": "2022-04-10T12:10:15.922Z",
  "updated_at": "2024-10-12T06:34:18.668Z",
  "registry_url": "https://pypi.org/project/pybtex-docutils/",
  "install_command": "pip install pybtex-docutils --index-url https://pypi.org/simple",
  "documentation_url": "https://pybtex-docutils.readthedocs.io/",
  "metadata": {
    "funding": null,
    "documentation": null,
    "classifiers": [
      "Development Status :: 5 - Production/Stable",
      "Environment :: Console",
      "Intended Audience :: Developers",
      "License :: OSI Approved :: MIT License",
      "Operating System :: OS Independent",
      "Programming Language :: Python",
      "Programming Language :: Python :: 3",
      "Programming Language :: Python :: 3.10",
      "Programming Language :: Python :: 3.11",
      "Programming Language :: Python :: 3.7",
      "Programming Language :: Python :: 3.8",
      "Programming Language :: Python :: 3.9",
      "Topic :: Text Editors :: Text Processing",
      "Topic :: Text Processing :: Markup :: XML"
    ],
    "normalized_name": "pybtex-docutils"
  },
  "repo_metadata": {
    "uuid": "11945788",
    "full_name": "mcmtroffaes/pybtex-docutils",
    "owner": "mcmtroffaes",
    "description": "A docutils backend for pybtex.",
    "archived": false,
    "fork": false,
    "pushed_at": "2023-08-23T08:32:46.000Z",
    "size": 96,
    "stargazers_count": 0,
    "open_issues_count": 1,
    "forks_count": 3,
    "subscribers_count": 3,
    "default_branch": "develop",
    "last_synced_at": "2023-09-15T20:30:53.129Z",
    "etag": null,
    "topics": [],
    "latest_commit_sha": null,
    "homepage": null,
    "language": "Python",
    "has_issues": true,
    "has_wiki": null,
    "has_pages": null,
    "mirror_url": null,
    "source_name": null,
    "license": "other",
    "status": null,
    "scm": "git",
    "pull_requests_enabled": true,
    "icon_url": "https://github.com/mcmtroffaes.png",
    "metadata": {
      "files": {
        "readme": "README.rst",
        "changelog": "CHANGELOG.rst",
        "contributing": null,
        "funding": null,
        "license": "LICENSE.rst",
        "code_of_conduct": null,
        "threat_model": null,
        "audit": null,
        "citation": null,
        "codeowners": null,
        "security": null,
        "support": null
      }
    },
    "created_at": "2013-08-07T09:02:17.000Z",
    "updated_at": "2022-05-25T07:02:28.000Z",
    "dependencies_parsed_at": "2022-08-07T05:15:16.692Z",
    "dependency_job_id": null,
    "html_url": "https://github.com/mcmtroffaes/pybtex-docutils",
    "commit_stats": null,
    "previous_names": [],
    "tags_count": 7,
    "repository_url": "https://repos.ecosyste.ms/api/v1/hosts/GitHub/repositories/mcmtroffaes%2Fpybtex-docutils",
    "tags_url": "https://repos.ecosyste.ms/api/v1/hosts/GitHub/repositories/mcmtroffaes%2Fpybtex-docutils/tags",
    "releases_url": "https://repos.ecosyste.ms/api/v1/hosts/GitHub/repositories/mcmtroffaes%2Fpybtex-docutils/releases",
    "manifests_url": "https://repos.ecosyste.ms/api/v1/hosts/GitHub/repositories/mcmtroffaes%2Fpybtex-docutils/manifests",
    "owner_url": "https://repos.ecosyste.ms/api/v1/hosts/GitHub/owners/mcmtroffaes",
    "download_url": "https://codeload.github.com/mcmtroffaes/pybtex-docutils/tar.gz/refs/heads/develop",
    "host": {
      "name": "GitHub",
      "url": "https://github.com",
      "kind": "github",
      "repositories_count": 160612894,
      "owners_count": 8196904,
      "icon_url": "https://github.com/github.png",
      "host_url": "https://repos.ecosyste.ms/api/v1/hosts/GitHub",
      "repositories_url": "https://repos.ecosyste.ms/api/v1/hosts/GitHub/repositories",
      "repository_names_url": "https://repos.ecosyste.ms/api/v1/hosts/GitHub/repository_names",
      "owners_url": "https://repos.ecosyste.ms/api/v1/hosts/GitHub/owners"
    },
    "owner_record": {
      "login": "mcmtroffaes",
      "name": "Matthias C. M. Troffaes",
      "uuid": "158568",
      "kind": "user",
      "description": null,
      "email": "",
      "website": null,
      "location": null,
      "twitter": null,
      "company": null,
      "icon_url": "https://avatars.githubusercontent.com/u/158568?v=4",
      "repositories_count": 48,
      "last_synced_at": "2023-04-09T19:27:09.232Z",
      "metadata": {
        "has_sponsors_listing": false
      },
      "html_url": "https://github.com/mcmtroffaes",
      "created_at": "2022-11-02T16:30:07.671Z",
      "updated_at": "2023-04-09T19:27:09.268Z",
      "owner_url": "https://repos.ecosyste.ms/api/v1/hosts/GitHub/owners/mcmtroffaes",
      "repositories_url": "https://repos.ecosyste.ms/api/v1/hosts/GitHub/owners/mcmtroffaes/repositories"
    },
    "tags": [
      {
        "name": "1.0.2",
        "sha": "af0bc4622007ecc62911ca5ea3dd450b5d0c7a9e",
        "kind": "tag",
        "published_at": "2022-05-25T12:41:50.000Z",
        "download_url": "https://codeload.github.com/mcmtroffaes/pybtex-docutils/tar.gz/1.0.2",
        "html_url": "https://github.com/mcmtroffaes/pybtex-docutils/releases/tag/1.0.2",
        "dependencies_parsed_at": null,
        "dependency_job_id": null,
        "tag_url": "https://repos.ecosyste.ms/api/v1/hosts/GitHub/repositories/mcmtroffaes%2Fpybtex-docutils/tags/1.0.2",
        "manifests_url": "https://repos.ecosyste.ms/api/v1/hosts/GitHub/repositories/mcmtroffaes%2Fpybtex-docutils/tags/1.0.2/manifests"
      },
      {
        "name": "1.0.1",
        "sha": "3b207454988d54e3e5d2c2705393a4b4d776ba9b",
        "kind": "tag",
        "published_at": "2021-07-29T12:39:06.000Z",
        "download_url": "https://codeload.github.com/mcmtroffaes/pybtex-docutils/tar.gz/1.0.1",
        "html_url": "https://github.com/mcmtroffaes/pybtex-docutils/releases/tag/1.0.1",
        "dependencies_parsed_at": null,
        "dependency_job_id": null,
        "tag_url": "https://repos.ecosyste.ms/api/v1/hosts/GitHub/repositories/mcmtroffaes%2Fpybtex-docutils/tags/1.0.1",
        "manifests_url": "https://repos.ecosyste.ms/api/v1/hosts/GitHub/repositories/mcmtroffaes%2Fpybtex-docutils/tags/1.0.1/manifests"
      },
      {
        "name": "1.0.0",
        "sha": "b8e89e3ffa80de066e3f3bd57716482ca297d731",
        "kind": "tag",
        "published_at": "2021-01-15T16:55:45.000Z",
        "download_url": "https://codeload.github.com/mcmtroffaes/pybtex-docutils/tar.gz/1.0.0",
        "html_url": "https://github.com/mcmtroffaes/pybtex-docutils/releases/tag/1.0.0",
        "dependencies_parsed_at": null,
        "dependency_job_id": null,
        "tag_url": "https://repos.ecosyste.ms/api/v1/hosts/GitHub/repositories/mcmtroffaes%2Fpybtex-docutils/tags/1.0.0",
        "manifests_url": "https://repos.ecosyste.ms/api/v1/hosts/GitHub/repositories/mcmtroffaes%2Fpybtex-docutils/tags/1.0.0/manifests"
      },
      {
        "name": "0.2.2",
        "sha": "1698da632853a22416a6382d27945eb926c9967c",
        "kind": "tag",
        "published_at": "2020-11-11T12:47:00.000Z",
        "download_url": "https://codeload.github.com/mcmtroffaes/pybtex-docutils/tar.gz/0.2.2",
        "html_url": "https://github.com/mcmtroffaes/pybtex-docutils/releases/tag/0.2.2",
        "dependencies_parsed_at": null,
        "dependency_job_id": null,
        "tag_url": "https://repos.ecosyste.ms/api/v1/hosts/GitHub/repositories/mcmtroffaes%2Fpybtex-docutils/tags/0.2.2",
        "manifests_url": "https://repos.ecosyste.ms/api/v1/hosts/GitHub/repositories/mcmtroffaes%2Fpybtex-docutils/tags/0.2.2/manifests"
      },
      {
        "name": "0.2.1",
        "sha": "bcdc8927bdfb1f53b14e0424bf9f7bedd8f62b11",
        "kind": "tag",
        "published_at": "2014-12-08T08:54:02.000Z",
        "download_url": "https://codeload.github.com/mcmtroffaes/pybtex-docutils/tar.gz/0.2.1",
        "html_url": "https://github.com/mcmtroffaes/pybtex-docutils/releases/tag/0.2.1",
        "dependencies_parsed_at": null,
        "dependency_job_id": null,
        "tag_url": "https://repos.ecosyste.ms/api/v1/hosts/GitHub/repositories/mcmtroffaes%2Fpybtex-docutils/tags/0.2.1",
        "manifests_url": "https://repos.ecosyste.ms/api/v1/hosts/GitHub/repositories/mcmtroffaes%2Fpybtex-docutils/tags/0.2.1/manifests"
      },
      {
        "name": "0.2.0",
        "sha": "d7bd51609e1343eb4bd07d47cb991787914fbcf0",
        "kind": "tag",
        "published_at": "2013-08-08T15:37:16.000Z",
        "download_url": "https://codeload.github.com/mcmtroffaes/pybtex-docutils/tar.gz/0.2.0",
        "html_url": "https://github.com/mcmtroffaes/pybtex-docutils/releases/tag/0.2.0",
        "dependencies_parsed_at": null,
        "dependency_job_id": null,
        "tag_url": "https://repos.ecosyste.ms/api/v1/hosts/GitHub/repositories/mcmtroffaes%2Fpybtex-docutils/tags/0.2.0",
        "manifests_url": "https://repos.ecosyste.ms/api/v1/hosts/GitHub/repositories/mcmtroffaes%2Fpybtex-docutils/tags/0.2.0/manifests"
      },
      {
        "name": "0.1.0",
        "sha": "4484f63635f55f585b83f59c6b07cb79a499e091",
        "kind": "tag",
        "published_at": "2013-08-07T11:55:26.000Z",
        "download_url": "https://codeload.github.com/mcmtroffaes/pybtex-docutils/tar.gz/0.1.0",
        "html_url": "https://github.com/mcmtroffaes/pybtex-docutils/releases/tag/0.1.0",
        "dependencies_parsed_at": null,
        "dependency_job_id": null,
        "tag_url": "https://repos.ecosyste.ms/api/v1/hosts/GitHub/repositories/mcmtroffaes%2Fpybtex-docutils/tags/0.1.0",
        "manifests_url": "https://repos.ecosyste.ms/api/v1/hosts/GitHub/repositories/mcmtroffaes%2Fpybtex-docutils/tags/0.1.0/manifests"
      }
    ]
  },
  "repo_metadata_updated_at": "2023-09-24T12:20:46.582Z",
  "dependent_packages_count": 4,
  "downloads": 718886,
  "downloads_period": "last-month",
  "dependent_repos_count": 435,
  "rankings": {
    "downloads": 0.6355509515039902,
    "dependent_repos_count": 0.6888812154696133,
    "dependent_packages_count": 2.3327095628808596,
    "stargazers_count": 38.81869497540387,
    "forks_count": 16.855366674279924,
    "docker_downloads_count": 1.3679788213627992,
    "average": 10.116530366816843
  },
  "purl": "pkg:pypi/pybtex-docutils",
  "advisories": [],
  "docker_usage_url": "https://docker.ecosyste.ms/usage/pypi/pybtex-docutils",
  "docker_dependents_count": 65,
  "docker_downloads_count": 18867,
  "usage_url": "https://repos.ecosyste.ms/usage/pypi/pybtex-docutils",
  "dependent_repositories_url": "https://repos.ecosyste.ms/api/v1/usage/pypi/pybtex-docutils/dependencies",
  "status": null,
  "funding_links": [],
  "critical": null,
  "versions_url": "https://packages.ecosyste.ms/api/v1/registries/pypi.org/packages/pybtex-docutils/versions",
  "version_numbers_url": "https://packages.ecosyste.ms/api/v1/registries/pypi.org/packages/pybtex-docutils/version_numbers",
  "dependent_packages_url": "https://packages.ecosyste.ms/api/v1/registries/pypi.org/packages/pybtex-docutils/dependent_packages",
  "related_packages_url": "https://packages.ecosyste.ms/api/v1/registries/pypi.org/packages/pybtex-docutils/related_packages",
  "maintainers": [
    {
      "uuid": "mcmtroffaes",
      "login": "mcmtroffaes",
      "name": null,
      "email": null,
      "url": null,
      "packages_count": 6,
      "html_url": "https://pypi.org/user/mcmtroffaes/",
      "role": null,
      "created_at": "2023-02-25T02:52:30.122Z",
      "updated_at": "2023-02-25T02:52:30.122Z",
      "packages_url": "https://packages.ecosyste.ms/api/v1/registries/pypi.org/maintainers/mcmtroffaes/packages"
    }
  ]
}