{
    "id": 657426,
    "name": "opis\/json-schema",
    "ecosystem": "packagist",
    "description": "Json Schema Validator for PHP",
    "homepage": "https:\/\/opis.io\/json-schema",
    "licenses": "Apache-2.0",
    "normalized_licenses": [
        "Apache-2.0"
    ],
    "repository_url": "https:\/\/github.com\/opis\/json-schema",
    "keywords_array": [
        "json",
        "schema",
        "validator",
        "validation",
        "json-schema"
    ],
    "namespace": "opis",
    "versions_count": 26,
    "first_release_published_at": "2017-12-04T14:45:27.000Z",
    "latest_release_published_at": "2022-01-08T20:38:03.000Z",
    "latest_release_number": "2.3.0",
    "last_synced_at": "2024-10-20T13:45:37.170Z",
    "created_at": "2022-04-07T10:33:42.004Z",
    "updated_at": "2024-10-20T13:45:37.170Z",
    "registry_url": "https:\/\/packagist.org\/packages\/opis\/json-schema#",
    "install_command": "composer require opis\/json-schema",
    "documentation_url": null,
    "metadata": {
        "funding": []
    },
    "repo_metadata": {
        "id": 37549551,
        "uuid": "112801482",
        "full_name": "opis\/json-schema",
        "owner": "opis",
        "description": "JSON Schema validator for PHP",
        "archived": false,
        "fork": false,
        "pushed_at": "2024-05-22T21:24:41.000Z",
        "size": 740,
        "stargazers_count": 558,
        "open_issues_count": 34,
        "forks_count": 56,
        "subscribers_count": 17,
        "default_branch": "master",
        "last_synced_at": "2024-09-05T01:05:26.371Z",
        "etag": null,
        "topics": [
            "json-pointer",
            "json-schema",
            "opis",
            "php"
        ],
        "latest_commit_sha": null,
        "homepage": "https:\/\/opis.io\/json-schema",
        "language": "PHP",
        "has_issues": true,
        "has_wiki": null,
        "has_pages": null,
        "mirror_url": null,
        "source_name": null,
        "license": "apache-2.0",
        "status": null,
        "scm": "git",
        "pull_requests_enabled": true,
        "icon_url": "https:\/\/github.com\/opis.png",
        "metadata": {
            "files": {
                "readme": "README.md",
                "changelog": null,
                "contributing": null,
                "funding": null,
                "license": "LICENSE",
                "code_of_conduct": null,
                "threat_model": null,
                "audit": null,
                "citation": null,
                "codeowners": null,
                "security": "SECURITY.md",
                "support": null,
                "governance": null,
                "roadmap": null,
                "authors": null,
                "dei": null,
                "publiccode": null,
                "codemeta": null
            }
        },
        "created_at": "2017-12-02T01:02:24.000Z",
        "updated_at": "2024-08-26T09:54:15.000Z",
        "dependencies_parsed_at": "2024-06-18T10:58:31.018Z",
        "dependency_job_id": null,
        "html_url": "https:\/\/github.com\/opis\/json-schema",
        "commit_stats": {
            "total_commits": 175,
            "total_committers": 16,
            "mean_commits": 10.9375,
            "dds": 0.2571428571428571,
            "last_synced_commit": "c48df6d7089a45f01e1c82432348f2d5976f9bfb"
        },
        "previous_names": [],
        "tags_count": 26,
        "template": false,
        "template_full_name": null,
        "repository_url": "https:\/\/repos.ecosyste.ms\/api\/v1\/hosts\/GitHub\/repositories\/opis%2Fjson-schema",
        "tags_url": "https:\/\/repos.ecosyste.ms\/api\/v1\/hosts\/GitHub\/repositories\/opis%2Fjson-schema\/tags",
        "releases_url": "https:\/\/repos.ecosyste.ms\/api\/v1\/hosts\/GitHub\/repositories\/opis%2Fjson-schema\/releases",
        "manifests_url": "https:\/\/repos.ecosyste.ms\/api\/v1\/hosts\/GitHub\/repositories\/opis%2Fjson-schema\/manifests",
        "owner_url": "https:\/\/repos.ecosyste.ms\/api\/v1\/hosts\/GitHub\/owners\/opis",
        "download_url": "https:\/\/codeload.github.com\/opis\/json-schema\/tar.gz\/refs\/heads\/master",
        "host": {
            "name": "GitHub",
            "url": "https:\/\/github.com",
            "kind": "github",
            "repositories_count": 217891094,
            "owners_count": 16246726,
            "icon_url": "https:\/\/github.com\/github.png",
            "version": null,
            "created_at": "2022-05-30T11:31:42.601Z",
            "updated_at": "2022-07-04T15:15:14.044Z",
            "host_url": "https:\/\/repos.ecosyste.ms\/api\/v1\/hosts\/GitHub",
            "repositories_url": "https:\/\/repos.ecosyste.ms\/api\/v1\/hosts\/GitHub\/repositories",
            "repository_names_url": "https:\/\/repos.ecosyste.ms\/api\/v1\/hosts\/GitHub\/repository_names",
            "owners_url": "https:\/\/repos.ecosyste.ms\/api\/v1\/hosts\/GitHub\/owners"
        },
        "owner_record": {
            "login": "opis",
            "name": "Opis",
            "uuid": "5928852",
            "kind": "organization",
            "description": "A fantastic collection of well crafted,  developer-focused, open source libraries",
            "email": null,
            "website": "https:\/\/opis.io",
            "location": null,
            "twitter": "OpisPHP",
            "company": null,
            "icon_url": "https:\/\/avatars.githubusercontent.com\/u\/5928852?v=4",
            "repositories_count": 25,
            "last_synced_at": "2024-03-25T20:07:50.908Z",
            "metadata": {
                "has_sponsors_listing": false
            },
            "html_url": "https:\/\/github.com\/opis",
            "funding_links": [],
            "total_stars": 3343,
            "followers": 14,
            "following": 0,
            "created_at": "2022-11-02T16:26:49.819Z",
            "updated_at": "2024-03-25T20:07:50.921Z",
            "owner_url": "https:\/\/repos.ecosyste.ms\/api\/v1\/hosts\/GitHub\/owners\/opis",
            "repositories_url": "https:\/\/repos.ecosyste.ms\/api\/v1\/hosts\/GitHub\/owners\/opis\/repositories"
        },
        "tags": [
            {
                "name": "2.3.0",
                "sha": "c48df6d7089a45f01e1c82432348f2d5976f9bfb",
                "kind": "commit",
                "published_at": "2022-01-08T20:38:03.000Z",
                "download_url": "https:\/\/codeload.github.com\/opis\/json-schema\/tar.gz\/2.3.0",
                "html_url": "https:\/\/github.com\/opis\/json-schema\/releases\/tag\/2.3.0",
                "dependencies_parsed_at": null,
                "dependency_job_id": null,
                "tag_url": "https:\/\/repos.ecosyste.ms\/api\/v1\/hosts\/GitHub\/repositories\/opis%2Fjson-schema\/tags\/2.3.0",
                "manifests_url": "https:\/\/repos.ecosyste.ms\/api\/v1\/hosts\/GitHub\/repositories\/opis%2Fjson-schema\/tags\/2.3.0\/manifests"
            },
            {
                "name": "2.2.0",
                "sha": "9ff2919681446bdd1e5ca5aeed9566a53f55bd75",
                "kind": "commit",
                "published_at": "2021-10-12T20:47:35.000Z",
                "download_url": "https:\/\/codeload.github.com\/opis\/json-schema\/tar.gz\/2.2.0",
                "html_url": "https:\/\/github.com\/opis\/json-schema\/releases\/tag\/2.2.0",
                "dependencies_parsed_at": null,
                "dependency_job_id": null,
                "tag_url": "https:\/\/repos.ecosyste.ms\/api\/v1\/hosts\/GitHub\/repositories\/opis%2Fjson-schema\/tags\/2.2.0",
                "manifests_url": "https:\/\/repos.ecosyste.ms\/api\/v1\/hosts\/GitHub\/repositories\/opis%2Fjson-schema\/tags\/2.2.0\/manifests"
            },
            {
                "name": "2.1.0",
                "sha": "a53152a70c2fe1f122da7bed7c37c01802dcf50c",
                "kind": "commit",
                "published_at": "2021-05-04T13:16:45.000Z",
                "download_url": "https:\/\/codeload.github.com\/opis\/json-schema\/tar.gz\/2.1.0",
                "html_url": "https:\/\/github.com\/opis\/json-schema\/releases\/tag\/2.1.0",
                "dependencies_parsed_at": null,
                "dependency_job_id": null,
                "tag_url": "https:\/\/repos.ecosyste.ms\/api\/v1\/hosts\/GitHub\/repositories\/opis%2Fjson-schema\/tags\/2.1.0",
                "manifests_url": "https:\/\/repos.ecosyste.ms\/api\/v1\/hosts\/GitHub\/repositories\/opis%2Fjson-schema\/tags\/2.1.0\/manifests"
            },
            {
                "name": "2.0.1",
                "sha": "2ddccb522482fadea41064f7c65fa942cb9fcb59",
                "kind": "commit",
                "published_at": "2021-04-21T15:34:32.000Z",
                "download_url": "https:\/\/codeload.github.com\/opis\/json-schema\/tar.gz\/2.0.1",
                "html_url": "https:\/\/github.com\/opis\/json-schema\/releases\/tag\/2.0.1",
                "dependencies_parsed_at": null,
                "dependency_job_id": null,
                "tag_url": "https:\/\/repos.ecosyste.ms\/api\/v1\/hosts\/GitHub\/repositories\/opis%2Fjson-schema\/tags\/2.0.1",
                "manifests_url": "https:\/\/repos.ecosyste.ms\/api\/v1\/hosts\/GitHub\/repositories\/opis%2Fjson-schema\/tags\/2.0.1\/manifests"
            },
            {
                "name": "1.1.0",
                "sha": "39d8072be8657a329a284339994401066406c43b",
                "kind": "tag",
                "published_at": "2021-04-14T20:05:40.000Z",
                "download_url": "https:\/\/codeload.github.com\/opis\/json-schema\/tar.gz\/1.1.0",
                "html_url": "https:\/\/github.com\/opis\/json-schema\/releases\/tag\/1.1.0",
                "dependencies_parsed_at": null,
                "dependency_job_id": null,
                "tag_url": "https:\/\/repos.ecosyste.ms\/api\/v1\/hosts\/GitHub\/repositories\/opis%2Fjson-schema\/tags\/1.1.0",
                "manifests_url": "https:\/\/repos.ecosyste.ms\/api\/v1\/hosts\/GitHub\/repositories\/opis%2Fjson-schema\/tags\/1.1.0\/manifests"
            },
            {
                "name": "2.0.0",
                "sha": "da4879f569b8f13b398ae621471708cec9033501",
                "kind": "tag",
                "published_at": "2021-04-13T19:31:32.000Z",
                "download_url": "https:\/\/codeload.github.com\/opis\/json-schema\/tar.gz\/2.0.0",
                "html_url": "https:\/\/github.com\/opis\/json-schema\/releases\/tag\/2.0.0",
                "dependencies_parsed_at": null,
                "dependency_job_id": null,
                "tag_url": "https:\/\/repos.ecosyste.ms\/api\/v1\/hosts\/GitHub\/repositories\/opis%2Fjson-schema\/tags\/2.0.0",
                "manifests_url": "https:\/\/repos.ecosyste.ms\/api\/v1\/hosts\/GitHub\/repositories\/opis%2Fjson-schema\/tags\/2.0.0\/manifests"
            },
            {
                "name": "1.0.19",
                "sha": "1bcb3582881d0692d002537a4472964280f71313",
                "kind": "commit",
                "published_at": "2020-06-07T20:56:25.000Z",
                "download_url": "https:\/\/codeload.github.com\/opis\/json-schema\/tar.gz\/1.0.19",
                "html_url": "https:\/\/github.com\/opis\/json-schema\/releases\/tag\/1.0.19",
                "dependencies_parsed_at": null,
                "dependency_job_id": null,
                "tag_url": "https:\/\/repos.ecosyste.ms\/api\/v1\/hosts\/GitHub\/repositories\/opis%2Fjson-schema\/tags\/1.0.19",
                "manifests_url": "https:\/\/repos.ecosyste.ms\/api\/v1\/hosts\/GitHub\/repositories\/opis%2Fjson-schema\/tags\/1.0.19\/manifests"
            },
            {
                "name": "1.0.18",
                "sha": "19868514d5e4c27553b21c7f0cf6388734c67d18",
                "kind": "commit",
                "published_at": "2019-05-22T05:16:45.000Z",
                "download_url": "https:\/\/codeload.github.com\/opis\/json-schema\/tar.gz\/1.0.18",
                "html_url": "https:\/\/github.com\/opis\/json-schema\/releases\/tag\/1.0.18",
                "dependencies_parsed_at": null,
                "dependency_job_id": null,
                "tag_url": "https:\/\/repos.ecosyste.ms\/api\/v1\/hosts\/GitHub\/repositories\/opis%2Fjson-schema\/tags\/1.0.18",
                "manifests_url": "https:\/\/repos.ecosyste.ms\/api\/v1\/hosts\/GitHub\/repositories\/opis%2Fjson-schema\/tags\/1.0.18\/manifests"
            },
            {
                "name": "1.0.17",
                "sha": "6e2782df93bc2b581639a583793e341529c56111",
                "kind": "commit",
                "published_at": "2019-05-10T19:07:20.000Z",
                "download_url": "https:\/\/codeload.github.com\/opis\/json-schema\/tar.gz\/1.0.17",
                "html_url": "https:\/\/github.com\/opis\/json-schema\/releases\/tag\/1.0.17",
                "dependencies_parsed_at": null,
                "dependency_job_id": null,
                "tag_url": "https:\/\/repos.ecosyste.ms\/api\/v1\/hosts\/GitHub\/repositories\/opis%2Fjson-schema\/tags\/1.0.17",
                "manifests_url": "https:\/\/repos.ecosyste.ms\/api\/v1\/hosts\/GitHub\/repositories\/opis%2Fjson-schema\/tags\/1.0.17\/manifests"
            },
            {
                "name": "1.0.16",
                "sha": "91f2464d44ffbaa34c3ee24e3bb6330690025859",
                "kind": "commit",
                "published_at": "2019-03-07T16:12:16.000Z",
                "download_url": "https:\/\/codeload.github.com\/opis\/json-schema\/tar.gz\/1.0.16",
                "html_url": "https:\/\/github.com\/opis\/json-schema\/releases\/tag\/1.0.16",
                "dependencies_parsed_at": null,
                "dependency_job_id": null,
                "tag_url": "https:\/\/repos.ecosyste.ms\/api\/v1\/hosts\/GitHub\/repositories\/opis%2Fjson-schema\/tags\/1.0.16",
                "manifests_url": "https:\/\/repos.ecosyste.ms\/api\/v1\/hosts\/GitHub\/repositories\/opis%2Fjson-schema\/tags\/1.0.16\/manifests"
            },
            {
                "name": "1.0.15",
                "sha": "ff5c65a03373bf5fbf6bf14a83d282e093091c8d",
                "kind": "commit",
                "published_at": "2019-01-18T14:11:57.000Z",
                "download_url": "https:\/\/codeload.github.com\/opis\/json-schema\/tar.gz\/1.0.15",
                "html_url": "https:\/\/github.com\/opis\/json-schema\/releases\/tag\/1.0.15",
                "dependencies_parsed_at": null,
                "dependency_job_id": null,
                "tag_url": "https:\/\/repos.ecosyste.ms\/api\/v1\/hosts\/GitHub\/repositories\/opis%2Fjson-schema\/tags\/1.0.15",
                "manifests_url": "https:\/\/repos.ecosyste.ms\/api\/v1\/hosts\/GitHub\/repositories\/opis%2Fjson-schema\/tags\/1.0.15\/manifests"
            },
            {
                "name": "1.0.14",
                "sha": "d79f9f4ab1dbbb88799b49cb4194d4229c4f6ef6",
                "kind": "commit",
                "published_at": "2019-01-16T15:54:41.000Z",
                "download_url": "https:\/\/codeload.github.com\/opis\/json-schema\/tar.gz\/1.0.14",
                "html_url": "https:\/\/github.com\/opis\/json-schema\/releases\/tag\/1.0.14",
                "dependencies_parsed_at": null,
                "dependency_job_id": null,
                "tag_url": "https:\/\/repos.ecosyste.ms\/api\/v1\/hosts\/GitHub\/repositories\/opis%2Fjson-schema\/tags\/1.0.14",
                "manifests_url": "https:\/\/repos.ecosyste.ms\/api\/v1\/hosts\/GitHub\/repositories\/opis%2Fjson-schema\/tags\/1.0.14\/manifests"
            },
            {
                "name": "1.0.13",
                "sha": "3dbf288ac08730bc864feaa449ca6e611387d284",
                "kind": "commit",
                "published_at": "2019-01-15T13:32:47.000Z",
                "download_url": "https:\/\/codeload.github.com\/opis\/json-schema\/tar.gz\/1.0.13",
                "html_url": "https:\/\/github.com\/opis\/json-schema\/releases\/tag\/1.0.13",
                "dependencies_parsed_at": null,
                "dependency_job_id": null,
                "tag_url": "https:\/\/repos.ecosyste.ms\/api\/v1\/hosts\/GitHub\/repositories\/opis%2Fjson-schema\/tags\/1.0.13",
                "manifests_url": "https:\/\/repos.ecosyste.ms\/api\/v1\/hosts\/GitHub\/repositories\/opis%2Fjson-schema\/tags\/1.0.13\/manifests"
            },
            {
                "name": "1.0.12",
                "sha": "cc89e90f6d8d1488f2057d245076f8857299d353",
                "kind": "commit",
                "published_at": "2019-01-09T12:25:41.000Z",
                "download_url": "https:\/\/codeload.github.com\/opis\/json-schema\/tar.gz\/1.0.12",
                "html_url": "https:\/\/github.com\/opis\/json-schema\/releases\/tag\/1.0.12",
                "dependencies_parsed_at": null,
                "dependency_job_id": null,
                "tag_url": "https:\/\/repos.ecosyste.ms\/api\/v1\/hosts\/GitHub\/repositories\/opis%2Fjson-schema\/tags\/1.0.12",
                "manifests_url": "https:\/\/repos.ecosyste.ms\/api\/v1\/hosts\/GitHub\/repositories\/opis%2Fjson-schema\/tags\/1.0.12\/manifests"
            },
            {
                "name": "1.0.11",
                "sha": "35ae1684273da5a12618e7c90200744af3c253fd",
                "kind": "tag",
                "published_at": "2018-10-31T16:47:08.000Z",
                "download_url": "https:\/\/codeload.github.com\/opis\/json-schema\/tar.gz\/1.0.11",
                "html_url": "https:\/\/github.com\/opis\/json-schema\/releases\/tag\/1.0.11",
                "dependencies_parsed_at": null,
                "dependency_job_id": null,
                "tag_url": "https:\/\/repos.ecosyste.ms\/api\/v1\/hosts\/GitHub\/repositories\/opis%2Fjson-schema\/tags\/1.0.11",
                "manifests_url": "https:\/\/repos.ecosyste.ms\/api\/v1\/hosts\/GitHub\/repositories\/opis%2Fjson-schema\/tags\/1.0.11\/manifests"
            },
            {
                "name": "1.0.10",
                "sha": "43ba67ae53ac7b3ba5e5ab4a1e1c75629a3031fc",
                "kind": "tag",
                "published_at": "2018-08-17T08:21:44.000Z",
                "download_url": "https:\/\/codeload.github.com\/opis\/json-schema\/tar.gz\/1.0.10",
                "html_url": "https:\/\/github.com\/opis\/json-schema\/releases\/tag\/1.0.10",
                "dependencies_parsed_at": null,
                "dependency_job_id": null,
                "tag_url": "https:\/\/repos.ecosyste.ms\/api\/v1\/hosts\/GitHub\/repositories\/opis%2Fjson-schema\/tags\/1.0.10",
                "manifests_url": "https:\/\/repos.ecosyste.ms\/api\/v1\/hosts\/GitHub\/repositories\/opis%2Fjson-schema\/tags\/1.0.10\/manifests"
            },
            {
                "name": "1.0.9",
                "sha": "89562ccff7864a9c952bd9f4219197068f612ba5",
                "kind": "tag",
                "published_at": "2018-05-23T10:59:39.000Z",
                "download_url": "https:\/\/codeload.github.com\/opis\/json-schema\/tar.gz\/1.0.9",
                "html_url": "https:\/\/github.com\/opis\/json-schema\/releases\/tag\/1.0.9",
                "dependencies_parsed_at": null,
                "dependency_job_id": null,
                "tag_url": "https:\/\/repos.ecosyste.ms\/api\/v1\/hosts\/GitHub\/repositories\/opis%2Fjson-schema\/tags\/1.0.9",
                "manifests_url": "https:\/\/repos.ecosyste.ms\/api\/v1\/hosts\/GitHub\/repositories\/opis%2Fjson-schema\/tags\/1.0.9\/manifests"
            },
            {
                "name": "1.0.8",
                "sha": "3a32e6021bd7e46152b6b7a9766b06a307f31f36",
                "kind": "tag",
                "published_at": "2018-05-22T11:48:26.000Z",
                "download_url": "https:\/\/codeload.github.com\/opis\/json-schema\/tar.gz\/1.0.8",
                "html_url": "https:\/\/github.com\/opis\/json-schema\/releases\/tag\/1.0.8",
                "dependencies_parsed_at": null,
                "dependency_job_id": null,
                "tag_url": "https:\/\/repos.ecosyste.ms\/api\/v1\/hosts\/GitHub\/repositories\/opis%2Fjson-schema\/tags\/1.0.8",
                "manifests_url": "https:\/\/repos.ecosyste.ms\/api\/v1\/hosts\/GitHub\/repositories\/opis%2Fjson-schema\/tags\/1.0.8\/manifests"
            },
            {
                "name": "1.0.7",
                "sha": "e0aaa234c3e3a1597ab9eeeb38919f254815ccf0",
                "kind": "tag",
                "published_at": "2018-04-05T19:43:39.000Z",
                "download_url": "https:\/\/codeload.github.com\/opis\/json-schema\/tar.gz\/1.0.7",
                "html_url": "https:\/\/github.com\/opis\/json-schema\/releases\/tag\/1.0.7",
                "dependencies_parsed_at": null,
                "dependency_job_id": null,
                "tag_url": "https:\/\/repos.ecosyste.ms\/api\/v1\/hosts\/GitHub\/repositories\/opis%2Fjson-schema\/tags\/1.0.7",
                "manifests_url": "https:\/\/repos.ecosyste.ms\/api\/v1\/hosts\/GitHub\/repositories\/opis%2Fjson-schema\/tags\/1.0.7\/manifests"
            },
            {
                "name": "1.0.6",
                "sha": "68a6897ed64c9ffdb5ac4cf0cfc380d9995fdbad",
                "kind": "tag",
                "published_at": "2018-04-01T20:06:28.000Z",
                "download_url": "https:\/\/codeload.github.com\/opis\/json-schema\/tar.gz\/1.0.6",
                "html_url": "https:\/\/github.com\/opis\/json-schema\/releases\/tag\/1.0.6",
                "dependencies_parsed_at": null,
                "dependency_job_id": null,
                "tag_url": "https:\/\/repos.ecosyste.ms\/api\/v1\/hosts\/GitHub\/repositories\/opis%2Fjson-schema\/tags\/1.0.6",
                "manifests_url": "https:\/\/repos.ecosyste.ms\/api\/v1\/hosts\/GitHub\/repositories\/opis%2Fjson-schema\/tags\/1.0.6\/manifests"
            },
            {
                "name": "1.0.5",
                "sha": "580add0ec56f2c89faeef8ae80461f1fcea9e2d9",
                "kind": "tag",
                "published_at": "2018-04-01T19:15:50.000Z",
                "download_url": "https:\/\/codeload.github.com\/opis\/json-schema\/tar.gz\/1.0.5",
                "html_url": "https:\/\/github.com\/opis\/json-schema\/releases\/tag\/1.0.5",
                "dependencies_parsed_at": null,
                "dependency_job_id": null,
                "tag_url": "https:\/\/repos.ecosyste.ms\/api\/v1\/hosts\/GitHub\/repositories\/opis%2Fjson-schema\/tags\/1.0.5",
                "manifests_url": "https:\/\/repos.ecosyste.ms\/api\/v1\/hosts\/GitHub\/repositories\/opis%2Fjson-schema\/tags\/1.0.5\/manifests"
            },
            {
                "name": "1.0.4",
                "sha": "2a8272491a296fc65b85b97b1e960ce4f6edff92",
                "kind": "tag",
                "published_at": "2018-02-27T15:58:01.000Z",
                "download_url": "https:\/\/codeload.github.com\/opis\/json-schema\/tar.gz\/1.0.4",
                "html_url": "https:\/\/github.com\/opis\/json-schema\/releases\/tag\/1.0.4",
                "dependencies_parsed_at": null,
                "dependency_job_id": null,
                "tag_url": "https:\/\/repos.ecosyste.ms\/api\/v1\/hosts\/GitHub\/repositories\/opis%2Fjson-schema\/tags\/1.0.4",
                "manifests_url": "https:\/\/repos.ecosyste.ms\/api\/v1\/hosts\/GitHub\/repositories\/opis%2Fjson-schema\/tags\/1.0.4\/manifests"
            },
            {
                "name": "1.0.3",
                "sha": "cde1b7c14163a1dae985b6c203e9b893d2254b5f",
                "kind": "tag",
                "published_at": "2017-12-28T16:52:19.000Z",
                "download_url": "https:\/\/codeload.github.com\/opis\/json-schema\/tar.gz\/1.0.3",
                "html_url": "https:\/\/github.com\/opis\/json-schema\/releases\/tag\/1.0.3",
                "dependencies_parsed_at": null,
                "dependency_job_id": null,
                "tag_url": "https:\/\/repos.ecosyste.ms\/api\/v1\/hosts\/GitHub\/repositories\/opis%2Fjson-schema\/tags\/1.0.3",
                "manifests_url": "https:\/\/repos.ecosyste.ms\/api\/v1\/hosts\/GitHub\/repositories\/opis%2Fjson-schema\/tags\/1.0.3\/manifests"
            },
            {
                "name": "1.0.2",
                "sha": "6bed00dfaa582cda23ea2333d60dce7cac96aa78",
                "kind": "tag",
                "published_at": "2017-12-07T18:29:23.000Z",
                "download_url": "https:\/\/codeload.github.com\/opis\/json-schema\/tar.gz\/1.0.2",
                "html_url": "https:\/\/github.com\/opis\/json-schema\/releases\/tag\/1.0.2",
                "dependencies_parsed_at": null,
                "dependency_job_id": null,
                "tag_url": "https:\/\/repos.ecosyste.ms\/api\/v1\/hosts\/GitHub\/repositories\/opis%2Fjson-schema\/tags\/1.0.2",
                "manifests_url": "https:\/\/repos.ecosyste.ms\/api\/v1\/hosts\/GitHub\/repositories\/opis%2Fjson-schema\/tags\/1.0.2\/manifests"
            },
            {
                "name": "1.0.1",
                "sha": "86c4f569b5a14f55495d8eede3cdd54b1ca7db3f",
                "kind": "tag",
                "published_at": "2017-12-06T11:21:41.000Z",
                "download_url": "https:\/\/codeload.github.com\/opis\/json-schema\/tar.gz\/1.0.1",
                "html_url": "https:\/\/github.com\/opis\/json-schema\/releases\/tag\/1.0.1",
                "dependencies_parsed_at": null,
                "dependency_job_id": null,
                "tag_url": "https:\/\/repos.ecosyste.ms\/api\/v1\/hosts\/GitHub\/repositories\/opis%2Fjson-schema\/tags\/1.0.1",
                "manifests_url": "https:\/\/repos.ecosyste.ms\/api\/v1\/hosts\/GitHub\/repositories\/opis%2Fjson-schema\/tags\/1.0.1\/manifests"
            },
            {
                "name": "1.0.0",
                "sha": "3d91bac43e2771551bc008f2c6b301b1ae7483c9",
                "kind": "tag",
                "published_at": "2017-12-04T14:49:13.000Z",
                "download_url": "https:\/\/codeload.github.com\/opis\/json-schema\/tar.gz\/1.0.0",
                "html_url": "https:\/\/github.com\/opis\/json-schema\/releases\/tag\/1.0.0",
                "dependencies_parsed_at": null,
                "dependency_job_id": null,
                "tag_url": "https:\/\/repos.ecosyste.ms\/api\/v1\/hosts\/GitHub\/repositories\/opis%2Fjson-schema\/tags\/1.0.0",
                "manifests_url": "https:\/\/repos.ecosyste.ms\/api\/v1\/hosts\/GitHub\/repositories\/opis%2Fjson-schema\/tags\/1.0.0\/manifests"
            }
        ]
    },
    "repo_metadata_updated_at": "2024-09-08T15:29:36.035Z",
    "dependent_packages_count": 134,
    "downloads": 18505624,
    "downloads_period": "total",
    "dependent_repos_count": 308,
    "rankings": {
        "downloads": 0.21487910504380323,
        "dependent_repos_count": 0.5179724206424997,
        "dependent_packages_count": 0.24754051183839576,
        "stargazers_count": 0.578205399129764,
        "forks_count": 1.178833947362391,
        "docker_downloads_count": 0.12070743725887162,
        "average": 0.4763564702126209
    },
    "purl": "pkg:composer\/opis\/json-schema",
    "advisories": [],
    "docker_usage_url": "https:\/\/docker.ecosyste.ms\/usage\/packagist\/opis\/json-schema",
    "docker_dependents_count": 27,
    "docker_downloads_count": 50234440,
    "usage_url": "https:\/\/repos.ecosyste.ms\/usage\/packagist\/opis\/json-schema",
    "dependent_repositories_url": "https:\/\/repos.ecosyste.ms\/api\/v1\/usage\/packagist\/opis\/json-schema\/dependencies",
    "status": null,
    "funding_links": [],
    "critical": null,
    "versions_url": "https:\/\/packages.ecosyste.ms\/api\/v1\/registries\/packagist.org\/packages\/opis%2Fjson-schema\/versions",
    "version_numbers_url": "https:\/\/packages.ecosyste.ms\/api\/v1\/registries\/packagist.org\/packages\/opis%2Fjson-schema\/version_numbers",
    "dependent_packages_url": "https:\/\/packages.ecosyste.ms\/api\/v1\/registries\/packagist.org\/packages\/opis%2Fjson-schema\/dependent_packages",
    "related_packages_url": "https:\/\/packages.ecosyste.ms\/api\/v1\/registries\/packagist.org\/packages\/opis%2Fjson-schema\/related_packages",
    "maintainers": [
        {
            "uuid": "msarca",
            "login": "msarca",
            "name": null,
            "email": null,
            "url": null,
            "packages_count": 43,
            "html_url": "https:\/\/packagist.org\/users\/msarca",
            "role": null,
            "created_at": "2022-11-10T10:42:02.575Z",
            "updated_at": "2022-11-10T10:42:02.575Z",
            "packages_url": "https:\/\/packages.ecosyste.ms\/api\/v1\/registries\/packagist.org\/maintainers\/msarca\/packages"
        },
        {
            "uuid": "sorinsarca",
            "login": "sorinsarca",
            "name": null,
            "email": null,
            "url": null,
            "packages_count": 41,
            "html_url": "https:\/\/packagist.org\/users\/sorinsarca",
            "role": null,
            "created_at": "2022-11-10T10:42:02.579Z",
            "updated_at": "2022-11-10T10:42:02.579Z",
            "packages_url": "https:\/\/packages.ecosyste.ms\/api\/v1\/registries\/packagist.org\/maintainers\/sorinsarca\/packages"
        }
    ]
}